django_mail_template/__init__.py
django_mail_template/admin.py
django_mail_template/apps.py
django_mail_template/models.py
django_mail_template/tools.py
django_mail_template/locale/es/LC_MESSAGES/django.mo
django_mail_template/locale/es/LC_MESSAGES/django.po
django_mail_template/migrations/0001_initial.py
django_mail_template/migrations/0002_auto_20200713_1814.py
django_mail_template/migrations/0003_auto_20200719_1722.py
django_mail_template/migrations/0004_auto_20200721_1922.py
django_mail_template/migrations/0005_auto_20200727_0642.py
django_mail_template/migrations/__init__.py
tests/__init__.py
tests/settings.py
tests/test_admin.py
tests/test_app.py
tests/test_functional.py
tests/test_models.py
tests/test_tools.py
tests/urls.py
django_mail_template-0.1.11.dist-info/LICENSE
django_mail_template-0.1.11.dist-info/METADATA
django_mail_template-0.1.11.dist-info/WHEEL
django_mail_template-0.1.11.dist-info/top_level.txt
django_mail_template-0.1.11.dist-info/RECORD
