Metadata-Version: 2.1
Name: django-mail-template
Version: 0.1.11
Summary: Application for creating mails templates with context variables. There is a double mapping between a mail template and process configuration so is possible to change used mail template of a process at run time.
Home-page: https://github.com/django-mail-template/master
Author: Vicente Ramos Garcia
Author-email: vramosga@gmail.com
License: BSD 3-clause
Platform: UNKNOWN
Classifier: Development Status :: 5 - Production/Stable
Classifier: Environment :: Web Environment
Classifier: Framework :: Django
Classifier: Framework :: Django :: 1.11
Classifier: Framework :: Django :: 2.0
Classifier: Framework :: Django :: 2.1
Classifier: Framework :: Django :: 2.2
Classifier: Framework :: Django :: 3.0
Classifier: Intended Audience :: Developers
Classifier: License :: OSI Approved :: BSD License
Classifier: Operating System :: OS Independent
Classifier: Programming Language :: Python
Classifier: Programming Language :: Python :: 3.5
Classifier: Programming Language :: Python :: 3.6
Classifier: Programming Language :: Python :: 3.7
Classifier: Programming Language :: Python :: 3.8
Classifier: Topic :: Communications :: Email
Requires-Dist: django-ckeditor
